scrapy_dynamic_spiders/__init__.py
scrapy_dynamic_spiders/factories/__init__.py
scrapy_dynamic_spiders/factories/base_factory.py
scrapy_dynamic_spiders/factories/crawl_spider_factory.py
scrapy_dynamic_spiders/utils/__init__.py
scrapy_dynamic_spiders/utils/factory_utils.py
scrapy_dynamic_spiders/wranglers/__init__.py
scrapy_dynamic_spiders/wranglers/base_wrangler.py
tests/__init__.py
tests/test_base_factory.py
tests/test_base_wrangler.py
tests/test_crawl_factory.py
tests/testing_spiders/__init__.py
tests/testing_spiders/spiders.py
scrapy_dynamic_spiders-1.0.0a1.dist-info/LICENSE
scrapy_dynamic_spiders-1.0.0a1.dist-info/METADATA
scrapy_dynamic_spiders-1.0.0a1.dist-info/WHEEL
scrapy_dynamic_spiders-1.0.0a1.dist-info/top_level.txt
scrapy_dynamic_spiders-1.0.0a1.dist-info/RECORD
