Metadata-Version: 2.1
Name: scrapy-dynamic-spiders
Version: 1.0.0a1
Summary: Dynamically generate spider subclasses. Run crawls sequentially with crochet. Do both.
Home-page: https://github.com/harootune/scrapy_dynamic_spiders
Author: Derek Harootune Otis
Author-email: dharootuneotis@gmail.com
License: UNKNOWN
Project-URL: Source, https://github.com/harootune/scrapy_dynamic_spiders
Keywords: scrapy spiders web-scraping
Platform: UNKNOWN
Classifier: Development Status :: 3 - Alpha
Classifier: Intended Audience :: Developers
Classifier: License :: OSI Approved :: MIT License
Classifier: Programming Language :: Python :: 3.6
Requires-Python: ~=3.6
Requires-Dist: scrapy
Requires-Dist: crochet
